cpca_new/__init__.py
cpca_new/drawer.py
cpca_new/exceptions.py
cpca_new/matcher.py
cpca_new/structures.py
cpca_new/resources/56_nations.csv
cpca_new/resources/__init__.py
cpca_new/resources/adcodes.csv
cpca_new-0.1.1.dist-info/licenses/LICENSE
cpca_new-0.1.1.dist-info/METADATA
cpca_new-0.1.1.dist-info/WHEEL
cpca_new-0.1.1.dist-info/top_level.txt
cpca_new-0.1.1.dist-info/RECORD
