Metadata-Version: 2.4
Name: cpca-new
Version: 0.1.1
Summary: Updated fork of cpca with refreshed adcodes data
Author: zl
License: The MIT License (MIT)
Requires-Python: >=3.6
License-File: LICENSE
Dynamic: license-file
